setup.py
CloudBase_OSS_PySDK.egg-info/PKG-INFO
CloudBase_OSS_PySDK.egg-info/SOURCES.txt
CloudBase_OSS_PySDK.egg-info/dependency_links.txt
CloudBase_OSS_PySDK.egg-info/not-zip-safe
CloudBase_OSS_PySDK.egg-info/top_level.txt
s3pysdk/__init__.py
s3pysdk/bucket.py
s3pysdk/connection.py
s3pysdk/models.py
s3pysdk/s3.py
s3pysdk/upload.py