Metadata-Version: 1.0
Name: CloudBase-OSS-PySDK
Version: 1.1
Summary: CloudBase OSS Python sdk
Home-page: http://https://nhanct@bitbucket.org/cloud360/s3-python-sdk.git
Author: HoangTO
Author-email: me@example.com
License: MIT
Platform: UNKNOWN
